[
    {
      "img": "https://webbox.imgix.net/images/owvecfmxulwbfvxm/7421591e-1ef6-4e85-b93c-94e5a105d39b.jpg?auto=format",
      "productId": "4d5c25f371c720a411eae1263d8c0af1603fbbe4",
      "productName": "Fixflex",
      "productType": "breakfast",
      "qty": 73,
      "price": {
        "currencyCode": "PHP",
        "value": 182
      }
    },
    {
      "img": "https://webbox.imgix.net/images/owvecfmxulwbfvxm/a92f9ff0-237d-41ea-b48c-58a92f61995e.jpg?auto=format",
      "productId": "74c14f0cd6d51f4cf2b5a7d3cb064023629537fa",
      "productName": "Biodex",
      "productType": "lunch",
      "qty": 39,
      "price": {
        "currencyCode": "PHP",
        "value": 560
      }
    },
    {
      "img": "https://webbox.imgix.net/images/owvecfmxulwbfvxm/a92f9ff0-237d-41ea-b48c-58a92f61995e.jpg?auto=format",
      "productId": "24343ff83113d2aa642feb4797dc9fa4324677a2",
      "productName": "Domainer",
      "productType": "dinner",
      "qty": 10,
      "price": {
        "currencyCode": "PHP",
        "value": 144
      }
    },
    {
      "img": "https://webbox.imgix.net/images/owvecfmxulwbfvxm/c56a0c0d-8454-431a-9b3e-f420c72e82e3.jpg?auto=format",
      "productId": "576345936cb62dd03ec5cef15010d54632ce35cb",
      "productName": "Flexidy",
      "productType": "msc",
      "qty": 69,
      "price": {
        "currencyCode": "PHP",
        "value": 907
      }
    },
    {
      "img": "https://webbox.imgix.net/images/owvecfmxulwbfvxm/a92f9ff0-237d-41ea-b48c-58a92f61995e.jpg?auto=format",
      "productId": "6ccf06e7251a70bfe81b3d45c21e3d6ca3d3acf2",
      "productName": "Cardguard",
      "productType": "breakfast",
      "qty": 94,
      "price": {
        "currencyCode": "PHP",
        "value": 575
      }
    },
    {
      "img": "https://webbox.imgix.net/images/owvecfmxulwbfvxm/a92f9ff0-237d-41ea-b48c-58a92f61995e.jpg?auto=format",
      "productId": "39186cc210d989140ee515cbdefca6273018603d",
      "productName": "Alphazap",
      "productType": "breakfast",
      "qty": 79,
      "price": {
        "currencyCode": "PHP",
        "value": 331
      }
    },
    {
      "img": "https://webbox.imgix.net/images/owvecfmxulwbfvxm/a92f9ff0-237d-41ea-b48c-58a92f61995e.jpg?auto=format",
      "productId": "ce132e3fc1029bff49800d3fbfe437cb09632c46",
      "productName": "Bitchip",
      "productType": "breakfast",
      "qty": 79,
      "price": {
        "currencyCode": "PHP",
        "value": 323
      }
    },
    {
      "img": "https://webbox.imgix.net/images/owvecfmxulwbfvxm/a92f9ff0-237d-41ea-b48c-58a92f61995e.jpg?auto=format",
      "productId": "b0a704ed6da7519ead9d1a44773dd181c796e5e1",
      "productName": "Tres-Zap",
      "productType": "dinner",
      "qty": 51,
      "price": {
        "currencyCode": "PHP",
        "value": 564
      }
    },
    {
      "img": "https://webbox.imgix.net/images/owvecfmxulwbfvxm/7421591e-1ef6-4e85-b93c-94e5a105d39b.jpg?auto=format",
      "productId": "23f7ef663b15d9bbc354d32269a6ef290e8730ea",
      "productName": "Sub-Ex",
      "productType": "room",
      "qty": 89,
      "price": {
        "currencyCode": "PHP",
        "value": 919
      }
    },
    {
      "img": "https://webbox.imgix.net/images/owvecfmxulwbfvxm/7421591e-1ef6-4e85-b93c-94e5a105d39b.jpg?auto=format",
      "productId": "b17d8c4841e19105858b64ffdab76c023918b1b6",
      "productName": "Tin",
      "productType": "breakfast",
      "qty": 22,
      "price": {
        "currencyCode": "PHP",
        "value": 750
      }
    },
    {
      "img": "https://webbox.imgix.net/images/owvecfmxulwbfvxm/c56a0c0d-8454-431a-9b3e-f420c72e82e3.jpg?auto=format",
      "productId": "211413ad75041010e6711f524c936aa2185d66b1",
      "productName": "Sonair",
      "productType": "dinner",
      "qty": 83,
      "price": {
        "currencyCode": "PHP",
        "value": 558
      }
    },
    {
      "img": "https://webbox.imgix.net/images/owvecfmxulwbfvxm/a92f9ff0-237d-41ea-b48c-58a92f61995e.jpg?auto=format",
      "productId": "c2c68364221bc520ff03e0fcff2bdde56d0d988d",
      "productName": "Job",
      "productType": "lunch",
      "qty": 42,
      "price": {
        "currencyCode": "PHP",
        "value": 257
      }
    },
    {
      "img": "https://webbox.imgix.net/images/owvecfmxulwbfvxm/7421591e-1ef6-4e85-b93c-94e5a105d39b.jpg?auto=format",
      "productId": "5ee52327f3440f7f37caf8f8488114f51d129f61",
      "productName": "Bytecard",
      "productType": "room",
      "qty": 10,
      "price": {
        "currencyCode": "PHP",
        "value": 892
      }
    },
    {
      "img": "https://webbox.imgix.net/images/owvecfmxulwbfvxm/c56a0c0d-8454-431a-9b3e-f420c72e82e3.jpg?auto=format",
      "productId": "2b74ae68ab101deef44d86d96e98f5269d5515cf",
      "productName": "Stronghold",
      "productType": "lunch",
      "qty": 76,
      "price": {
        "currencyCode": "PHP",
        "value": 976
      }
    },
    {
      "img": "https://webbox.imgix.net/images/owvecfmxulwbfvxm/7421591e-1ef6-4e85-b93c-94e5a105d39b.jpg?auto=format",
      "productId": "d34aaea337b1c83bfa374524d010bc270f47c6e3",
      "productName": "Toughjoyfax",
      "productType": "msc",
      "qty": 60,
      "price": {
        "currencyCode": "PHP",
        "value": 608
      }
    },
    {
      "img": "https://webbox.imgix.net/images/owvecfmxulwbfvxm/7421591e-1ef6-4e85-b93c-94e5a105d39b.jpg?auto=format",
      "productId": "c20bcfa15e5d87194866d81071b39bbed1592c6d",
      "productName": "Home Ing",
      "productType": "room",
      "qty": 79,
      "price": {
        "currencyCode": "PHP",
        "value": 592
      }
    },
    {
      "img": "https://webbox.imgix.net/images/owvecfmxulwbfvxm/7421591e-1ef6-4e85-b93c-94e5a105d39b.jpg?auto=format",
      "productId": "eb2659cd9d0fec59543697c9194eed1c0123f04d",
      "productName": "Wrapsafe",
      "productType": "msc",
      "qty": 3,
      "price": {
        "currencyCode": "PHP",
        "value": 366
      }
    },
    {
      "img": "https://webbox.imgix.net/images/owvecfmxulwbfvxm/c56a0c0d-8454-431a-9b3e-f420c72e82e3.jpg?auto=format",
      "productId": "93ddec54b75a9e24ae2941cf92b661528351eae1",
      "productName": "Zaam-Dox",
      "productType": "breakfast",
      "qty": 71,
      "price": {
        "currencyCode": "PHP",
        "value": 887
      }
    },
    {
      "img": "https://webbox.imgix.net/images/owvecfmxulwbfvxm/7421591e-1ef6-4e85-b93c-94e5a105d39b.jpg?auto=format",
      "productId": "8c232c21073f2583f72af3b2e223b4caf680c3e0",
      "productName": "Tresom",
      "productType": "breakfast",
      "qty": 81,
      "price": {
        "currencyCode": "PHP",
        "value": 940
      }
    },
    {
      "img": "https://webbox.imgix.net/images/owvecfmxulwbfvxm/a92f9ff0-237d-41ea-b48c-58a92f61995e.jpg?auto=format",
      "productId": "06a5a4e4a1ca376ece1ba9c75f96298864ee354e",
      "productName": "Daltfresh",
      "productType": "room",
      "qty": 11,
      "price": {
        "currencyCode": "PHP",
        "value": 21
      }
    },
    {
      "img": "https://webbox.imgix.net/images/owvecfmxulwbfvxm/c56a0c0d-8454-431a-9b3e-f420c72e82e3.jpg?auto=format",
      "productId": "aa78b0115dfc1d81b23d1c87775e6b3f00e9cbc8",
      "productName": "Treeflex",
      "productType": "dinner",
      "qty": 41,
      "price": {
        "currencyCode": "PHP",
        "value": 223
      }
    },
    {
      "img": "https://webbox.imgix.net/images/owvecfmxulwbfvxm/c56a0c0d-8454-431a-9b3e-f420c72e82e3.jpg?auto=format",
      "productId": "90e65aa091c2c544fd9342a5974b49d03d3b75ea",
      "productName": "Zontrax",
      "productType": "msc",
      "qty": 36,
      "price": {
        "currencyCode": "PHP",
        "value": 473
      }
    },
    {
      "img": "https://webbox.imgix.net/images/owvecfmxulwbfvxm/a92f9ff0-237d-41ea-b48c-58a92f61995e.jpg?auto=format",
      "productId": "502414fca788881640064a48ed340b71a4b5025f",
      "productName": "Konklux",
      "productType": "breakfast",
      "qty": 33,
      "price": {
        "currencyCode": "PHP",
        "value": 250
      }
    },
    {
      "img": "https://webbox.imgix.net/images/owvecfmxulwbfvxm/c56a0c0d-8454-431a-9b3e-f420c72e82e3.jpg?auto=format",
      "productId": "eae91b4b2097897d635b646adcf243fcf0fbe60d",
      "productName": "Sonair",
      "productType": "room",
      "qty": 83,
      "price": {
        "currencyCode": "PHP",
        "value": 954
      }
    },
    {
      "img": "https://webbox.imgix.net/images/owvecfmxulwbfvxm/c56a0c0d-8454-431a-9b3e-f420c72e82e3.jpg?auto=format",
      "productId": "e791849c3c7b265c028710af9005b514454cb628",
      "productName": "Cookley",
      "productType": "breakfast",
      "qty": 95,
      "price": {
        "currencyCode": "PHP",
        "value": 228
      }
    },
    {
      "img": "https://webbox.imgix.net/images/owvecfmxulwbfvxm/a92f9ff0-237d-41ea-b48c-58a92f61995e.jpg?auto=format",
      "productId": "b0ae230bfbb2c94b8c192528b1535eaec78eb900",
      "productName": "Opela",
      "productType": "msc",
      "qty": 95,
      "price": {
        "currencyCode": "PHP",
        "value": 977
      }
    },
    {
      "img": "https://webbox.imgix.net/images/owvecfmxulwbfvxm/c56a0c0d-8454-431a-9b3e-f420c72e82e3.jpg?auto=format",
      "productId": "1a936aa02d9af27250fb59e89f6b8fe8194ae6af",
      "productName": "Alpha",
      "productType": "room",
      "qty": 59,
      "price": {
        "currencyCode": "PHP",
        "value": 436
      }
    },
    {
      "img": "https://webbox.imgix.net/images/owvecfmxulwbfvxm/7421591e-1ef6-4e85-b93c-94e5a105d39b.jpg?auto=format",
      "productId": "2d2ffc1ddc80dbd93aabbd7e532d1726f4b84583",
      "productName": "Sonsing",
      "productType": "msc",
      "qty": 24,
      "price": {
        "currencyCode": "PHP",
        "value": 48
      }
    },
    {
      "img": "https://webbox.imgix.net/images/owvecfmxulwbfvxm/7421591e-1ef6-4e85-b93c-94e5a105d39b.jpg?auto=format",
      "productId": "b76d2208f58a2304e501c6b58552bb15af6941fd",
      "productName": "Voltsillam",
      "productType": "lunch",
      "qty": 46,
      "price": {
        "currencyCode": "PHP",
        "value": 372
      }
    },
    {
      "img": "https://webbox.imgix.net/images/owvecfmxulwbfvxm/a92f9ff0-237d-41ea-b48c-58a92f61995e.jpg?auto=format",
      "productId": "84cfabd956be5c15a936fef181f2ddef508ca7ac",
      "productName": "Bamity",
      "productType": "room",
      "qty": 71,
      "price": {
        "currencyCode": "PHP",
        "value": 356
      }
    },
    {
      "img": "https://webbox.imgix.net/images/owvecfmxulwbfvxm/7421591e-1ef6-4e85-b93c-94e5a105d39b.jpg?auto=format",
      "productId": "7b1c0d405b60a24b23407cd1df9a90cba1c2fd72",
      "productName": "Bamity",
      "productType": "room",
      "qty": 77,
      "price": {
        "currencyCode": "PHP",
        "value": 762
      }
    },
    {
      "img": "https://webbox.imgix.net/images/owvecfmxulwbfvxm/a92f9ff0-237d-41ea-b48c-58a92f61995e.jpg?auto=format",
      "productId": "d7d1cc92ef136912a18a80ff6f8eb7a4b40e77f4",
      "productName": "Gembucket",
      "productType": "breakfast",
      "qty": 74,
      "price": {
        "currencyCode": "PHP",
        "value": 942
      }
    },
    {
      "img": "https://webbox.imgix.net/images/owvecfmxulwbfvxm/7421591e-1ef6-4e85-b93c-94e5a105d39b.jpg?auto=format",
      "productId": "6d3e630c10732e4a7b2c67ffb704bfe6c432db04",
      "productName": "Tresom",
      "productType": "lunch",
      "qty": 14,
      "price": {
        "currencyCode": "PHP",
        "value": 540
      }
    },
    {
      "img": "https://webbox.imgix.net/images/owvecfmxulwbfvxm/a92f9ff0-237d-41ea-b48c-58a92f61995e.jpg?auto=format",
      "productId": "d07de9d05b97670070383a108ff301f2d2cea3c4",
      "productName": "Hatity",
      "productType": "room",
      "qty": 65,
      "price": {
        "currencyCode": "PHP",
        "value": 352
      }
    },
    {
      "img": "https://webbox.imgix.net/images/owvecfmxulwbfvxm/c56a0c0d-8454-431a-9b3e-f420c72e82e3.jpg?auto=format",
      "productId": "90f90c8f9acc058f58f24de40951e4a034741a57",
      "productName": "Toughjoyfax",
      "productType": "breakfast",
      "qty": 26,
      "price": {
        "currencyCode": "PHP",
        "value": 390
      }
    },
    {
      "img": "https://webbox.imgix.net/images/owvecfmxulwbfvxm/c56a0c0d-8454-431a-9b3e-f420c72e82e3.jpg?auto=format",
      "productId": "98c74b27fc7ce7b829ee6d022ffeaf80263b53de",
      "productName": "Regrant",
      "productType": "msc",
      "qty": 90,
      "price": {
        "currencyCode": "PHP",
        "value": 126
      }
    },
    {
      "img": "https://webbox.imgix.net/images/owvecfmxulwbfvxm/a92f9ff0-237d-41ea-b48c-58a92f61995e.jpg?auto=format",
      "productId": "95a2865e5975b6616fc361d5c4eb4693241e99d8",
      "productName": "It",
      "productType": "msc",
      "qty": 53,
      "price": {
        "currencyCode": "PHP",
        "value": 794
      }
    },
    {
      "img": "https://webbox.imgix.net/images/owvecfmxulwbfvxm/c56a0c0d-8454-431a-9b3e-f420c72e82e3.jpg?auto=format",
      "productId": "b6323908282d076df2fa7c891471be1e092c62dd",
      "productName": "Matsoft",
      "productType": "dinner",
      "qty": 13,
      "price": {
        "currencyCode": "PHP",
        "value": 538
      }
    },
    {
      "img": "https://webbox.imgix.net/images/owvecfmxulwbfvxm/a92f9ff0-237d-41ea-b48c-58a92f61995e.jpg?auto=format",
      "productId": "de10d33147f5a450dbc85fa806fa7889d3602ac0",
      "productName": "Bigtax",
      "productType": "lunch",
      "qty": 36,
      "price": {
        "currencyCode": "PHP",
        "value": 943
      }
    },
    {
      "img": "https://webbox.imgix.net/images/owvecfmxulwbfvxm/a92f9ff0-237d-41ea-b48c-58a92f61995e.jpg?auto=format",
      "productId": "fe3d310055f4d9fbcb59ed66706454506a2ae6e9",
      "productName": "Overhold",
      "productType": "breakfast",
      "qty": 79,
      "price": {
        "currencyCode": "PHP",
        "value": 90
      }
    },
    {
      "img": "https://webbox.imgix.net/images/owvecfmxulwbfvxm/c56a0c0d-8454-431a-9b3e-f420c72e82e3.jpg?auto=format",
      "productId": "4d375d7dd9251cb1e490470997782a49711e2bbf",
      "productName": "Rank",
      "productType": "room",
      "qty": 78,
      "price": {
        "currencyCode": "PHP",
        "value": 693
      }
    },
    {
      "img": "https://webbox.imgix.net/images/owvecfmxulwbfvxm/c56a0c0d-8454-431a-9b3e-f420c72e82e3.jpg?auto=format",
      "productId": "f31247435c9d653ae329e41d77b8dcdde4a4947f",
      "productName": "Sub-Ex",
      "productType": "lunch",
      "qty": 9,
      "price": {
        "currencyCode": "PHP",
        "value": 354
      }
    },
    {
      "img": "https://webbox.imgix.net/images/owvecfmxulwbfvxm/7421591e-1ef6-4e85-b93c-94e5a105d39b.jpg?auto=format",
      "productId": "afd646aafe94a7c7632af53697734d4ecdad5529",
      "productName": "Sub-Ex",
      "productType": "lunch",
      "qty": 98,
      "price": {
        "currencyCode": "PHP",
        "value": 605
      }
    },
    {
      "img": "https://webbox.imgix.net/images/owvecfmxulwbfvxm/c56a0c0d-8454-431a-9b3e-f420c72e82e3.jpg?auto=format",
      "productId": "1418a5fad9a938f9029c71f24d5d00e82f832692",
      "productName": "Fintone",
      "productType": "breakfast",
      "qty": 55,
      "price": {
        "currencyCode": "PHP",
        "value": 344
      }
    },
    {
      "img": "https://webbox.imgix.net/images/owvecfmxulwbfvxm/a92f9ff0-237d-41ea-b48c-58a92f61995e.jpg?auto=format",
      "productId": "b7f1762426ced270c7bb6f525c4207f8b30dd48c",
      "productName": "Flowdesk",
      "productType": "dinner",
      "qty": 74,
      "price": {
        "currencyCode": "PHP",
        "value": 167
      }
    },
    {
      "img": "https://webbox.imgix.net/images/owvecfmxulwbfvxm/c56a0c0d-8454-431a-9b3e-f420c72e82e3.jpg?auto=format",
      "productId": "7c3579f3dc167e47b34ae8a9ba76462032c850f5",
      "productName": "Latlux",
      "productType": "room",
      "qty": 2,
      "price": {
        "currencyCode": "PHP",
        "value": 361
      }
    },
    {
      "img": "https://webbox.imgix.net/images/owvecfmxulwbfvxm/c56a0c0d-8454-431a-9b3e-f420c72e82e3.jpg?auto=format",
      "productId": "d24c0cfb4d5cf87d5f1250285ac64a6ac284d92e",
      "productName": "Cardify",
      "productType": "breakfast",
      "qty": 53,
      "price": {
        "currencyCode": "PHP",
        "value": 456
      }
    },
    {
      "img": "https://webbox.imgix.net/images/owvecfmxulwbfvxm/c56a0c0d-8454-431a-9b3e-f420c72e82e3.jpg?auto=format",
      "productId": "af4dfa48e21143d111c596737b6a5ffbee47a4ad",
      "productName": "Zathin",
      "productType": "dinner",
      "qty": 13,
      "price": {
        "currencyCode": "PHP",
        "value": 858
      }
    },
    {
      "img": "https://webbox.imgix.net/images/owvecfmxulwbfvxm/7421591e-1ef6-4e85-b93c-94e5a105d39b.jpg?auto=format",
      "productId": "3bdb1946eb66b7888cf614ef41447117436b0806",
      "productName": "Tin",
      "productType": "lunch",
      "qty": 34,
      "price": {
        "currencyCode": "PHP",
        "value": 259
      }
    },
    {
      "img": "https://webbox.imgix.net/images/owvecfmxulwbfvxm/7421591e-1ef6-4e85-b93c-94e5a105d39b.jpg?auto=format",
      "productId": "09ee800e55b397a77cc78ab43e6524d7b0ff7b2b",
      "productName": "Fixflex",
      "productType": "lunch",
      "qty": 18,
      "price": {
        "currencyCode": "PHP",
        "value": 931
      }
    },
    {
      "img": "https://webbox.imgix.net/images/owvecfmxulwbfvxm/a92f9ff0-237d-41ea-b48c-58a92f61995e.jpg?auto=format",
      "productId": "d5ebb46e266eed0b3e34e80b7a2d9d3571e58033",
      "productName": "Ronstring",
      "productType": "room",
      "qty": 61,
      "price": {
        "currencyCode": "PHP",
        "value": 744
      }
    },
    {
      "img": "https://webbox.imgix.net/images/owvecfmxulwbfvxm/7421591e-1ef6-4e85-b93c-94e5a105d39b.jpg?auto=format",
      "productId": "270799c44779907427fa202fe7c3d061c579c908",
      "productName": "It",
      "productType": "msc",
      "qty": 85,
      "price": {
        "currencyCode": "PHP",
        "value": 704
      }
    },
    {
      "img": "https://webbox.imgix.net/images/owvecfmxulwbfvxm/7421591e-1ef6-4e85-b93c-94e5a105d39b.jpg?auto=format",
      "productId": "68b4e7fa73addd2d92384e7744e72587ca3f68c6",
      "productName": "Tresom",
      "productType": "msc",
      "qty": 8,
      "price": {
        "currencyCode": "PHP",
        "value": 487
      }
    },
    {
      "img": "https://webbox.imgix.net/images/owvecfmxulwbfvxm/c56a0c0d-8454-431a-9b3e-f420c72e82e3.jpg?auto=format",
      "productId": "d9364fc9cf6357af5273c6df9bf69cc5dcee2e01",
      "productName": "Transcof",
      "productType": "msc",
      "qty": 79,
      "price": {
        "currencyCode": "PHP",
        "value": 228
      }
    },
    {
      "img": "https://webbox.imgix.net/images/owvecfmxulwbfvxm/7421591e-1ef6-4e85-b93c-94e5a105d39b.jpg?auto=format",
      "productId": "db40743756f56026bded639a909187dcb08b2ba8",
      "productName": "Prodder",
      "productType": "msc",
      "qty": 85,
      "price": {
        "currencyCode": "PHP",
        "value": 586
      }
    },
    {
      "img": "https://webbox.imgix.net/images/owvecfmxulwbfvxm/7421591e-1ef6-4e85-b93c-94e5a105d39b.jpg?auto=format",
      "productId": "585cfaac4751c61f6138b6f7948c3415a43a01f3",
      "productName": "Opela",
      "productType": "lunch",
      "qty": 81,
      "price": {
        "currencyCode": "PHP",
        "value": 748
      }
    },
    {
      "img": "https://webbox.imgix.net/images/owvecfmxulwbfvxm/c56a0c0d-8454-431a-9b3e-f420c72e82e3.jpg?auto=format",
      "productId": "5540e9c7ae1e59169ee722480a80164a9f0ce539",
      "productName": "Holdlamis",
      "productType": "dinner",
      "qty": 59,
      "price": {
        "currencyCode": "PHP",
        "value": 574
      }
    },
    {
      "img": "https://webbox.imgix.net/images/owvecfmxulwbfvxm/c56a0c0d-8454-431a-9b3e-f420c72e82e3.jpg?auto=format",
      "productId": "75eff8f376abab7bec678c12aee09eef4d90f101",
      "productName": "Y-Solowarm",
      "productType": "room",
      "qty": 78,
      "price": {
        "currencyCode": "PHP",
        "value": 827
      }
    },
    {
      "img": "https://webbox.imgix.net/images/owvecfmxulwbfvxm/a92f9ff0-237d-41ea-b48c-58a92f61995e.jpg?auto=format",
      "productId": "a3494537933b8992eb33fd2c974c7037910f3bf5",
      "productName": "Cardguard",
      "productType": "lunch",
      "qty": 62,
      "price": {
        "currencyCode": "PHP",
        "value": 402
      }
    },
    {
      "img": "https://webbox.imgix.net/images/owvecfmxulwbfvxm/a92f9ff0-237d-41ea-b48c-58a92f61995e.jpg?auto=format",
      "productId": "08106bc98bbfe9ecf424c573f02af7a12e8d3152",
      "productName": "Keylex",
      "productType": "breakfast",
      "qty": 53,
      "price": {
        "currencyCode": "PHP",
        "value": 56
      }
    },
    {
      "img": "https://webbox.imgix.net/images/owvecfmxulwbfvxm/7421591e-1ef6-4e85-b93c-94e5a105d39b.jpg?auto=format",
      "productId": "0655cac1fc9fe7fc1c1868272306b2283f03a949",
      "productName": "Transcof",
      "productType": "breakfast",
      "qty": 1,
      "price": {
        "currencyCode": "PHP",
        "value": 433
      }
    },
    {
      "img": "https://webbox.imgix.net/images/owvecfmxulwbfvxm/c56a0c0d-8454-431a-9b3e-f420c72e82e3.jpg?auto=format",
      "productId": "b7b9c7d91c3fc2e02ffd2b85a6eaf87a6285ff41",
      "productName": "Zontrax",
      "productType": "dinner",
      "qty": 30,
      "price": {
        "currencyCode": "PHP",
        "value": 928
      }
    },
    {
      "img": "https://webbox.imgix.net/images/owvecfmxulwbfvxm/7421591e-1ef6-4e85-b93c-94e5a105d39b.jpg?auto=format",
      "productId": "47705a0da2a413b0e38e560f24d7002a864417f2",
      "productName": "Kanlam",
      "productType": "dinner",
      "qty": 89,
      "price": {
        "currencyCode": "PHP",
        "value": 881
      }
    },
    {
      "img": "https://webbox.imgix.net/images/owvecfmxulwbfvxm/7421591e-1ef6-4e85-b93c-94e5a105d39b.jpg?auto=format",
      "productId": "ac46b97993d9f4479dfa0689ddae5ef9eb435b78",
      "productName": "Fix San",
      "productType": "msc",
      "qty": 55,
      "price": {
        "currencyCode": "PHP",
        "value": 106
      }
    },
    {
      "img": "https://webbox.imgix.net/images/owvecfmxulwbfvxm/a92f9ff0-237d-41ea-b48c-58a92f61995e.jpg?auto=format",
      "productId": "e10b9b963341ac82000633643f159aeff1193bbc",
      "productName": "Fix San",
      "productType": "msc",
      "qty": 41,
      "price": {
        "currencyCode": "PHP",
        "value": 302
      }
    },
    {
      "img": "https://webbox.imgix.net/images/owvecfmxulwbfvxm/a92f9ff0-237d-41ea-b48c-58a92f61995e.jpg?auto=format",
      "productId": "955b8e23c0d6a1005b4d3089f4ee5706ac098567",
      "productName": "Solarbreeze",
      "productType": "dinner",
      "qty": 40,
      "price": {
        "currencyCode": "PHP",
        "value": 256
      }
    },
    {
      "img": "https://webbox.imgix.net/images/owvecfmxulwbfvxm/c56a0c0d-8454-431a-9b3e-f420c72e82e3.jpg?auto=format",
      "productId": "9da949fd8b8523b18614fd6c84bf9d65df47ef04",
      "productName": "Hatity",
      "productType": "msc",
      "qty": 73,
      "price": {
        "currencyCode": "PHP",
        "value": 439
      }
    },
    {
      "img": "https://webbox.imgix.net/images/owvecfmxulwbfvxm/c56a0c0d-8454-431a-9b3e-f420c72e82e3.jpg?auto=format",
      "productId": "85e32bd9049787abcc36aeafbeaeab1e5f37ccf5",
      "productName": "Wrapsafe",
      "productType": "lunch",
      "qty": 44,
      "price": {
        "currencyCode": "PHP",
        "value": 343
      }
    },
    {
      "img": "https://webbox.imgix.net/images/owvecfmxulwbfvxm/7421591e-1ef6-4e85-b93c-94e5a105d39b.jpg?auto=format",
      "productId": "a6966718fbc29f8a5e26cf5b753b3c521c837c13",
      "productName": "Tampflex",
      "productType": "dinner",
      "qty": 32,
      "price": {
        "currencyCode": "PHP",
        "value": 172
      }
    },
    {
      "img": "https://webbox.imgix.net/images/owvecfmxulwbfvxm/c56a0c0d-8454-431a-9b3e-f420c72e82e3.jpg?auto=format",
      "productId": "2c0fcd7f7b69506a240519772fb362f87a1f867d",
      "productName": "It",
      "productType": "dinner",
      "qty": 59,
      "price": {
        "currencyCode": "PHP",
        "value": 944
      }
    },
    {
      "img": "https://webbox.imgix.net/images/owvecfmxulwbfvxm/7421591e-1ef6-4e85-b93c-94e5a105d39b.jpg?auto=format",
      "productId": "1f19cd5c77bb1df8a7e86ac61f14d16a7a60128a",
      "productName": "Zamit",
      "productType": "dinner",
      "qty": 82,
      "price": {
        "currencyCode": "PHP",
        "value": 216
      }
    },
    {
      "img": "https://webbox.imgix.net/images/owvecfmxulwbfvxm/a92f9ff0-237d-41ea-b48c-58a92f61995e.jpg?auto=format",
      "productId": "70d97706ae3b4a0f9faa7a8015daedc0896d6ef6",
      "productName": "Tempsoft",
      "productType": "dinner",
      "qty": 67,
      "price": {
        "currencyCode": "PHP",
        "value": 241
      }
    },
    {
      "img": "https://webbox.imgix.net/images/owvecfmxulwbfvxm/a92f9ff0-237d-41ea-b48c-58a92f61995e.jpg?auto=format",
      "productId": "289a49b2185dabf635c1486d4cf5a41ec1ea8c58",
      "productName": "Span",
      "productType": "msc",
      "qty": 57,
      "price": {
        "currencyCode": "PHP",
        "value": 701
      }
    },
    {
      "img": "https://webbox.imgix.net/images/owvecfmxulwbfvxm/c56a0c0d-8454-431a-9b3e-f420c72e82e3.jpg?auto=format",
      "productId": "ecc57708456af8a1581c8f786843fbdf1ada6238",
      "productName": "Latlux",
      "productType": "room",
      "qty": 42,
      "price": {
        "currencyCode": "PHP",
        "value": 196
      }
    },
    {
      "img": "https://webbox.imgix.net/images/owvecfmxulwbfvxm/a92f9ff0-237d-41ea-b48c-58a92f61995e.jpg?auto=format",
      "productId": "64425ca22ffcb7e5b53ee2f430599b2bcd3e576b",
      "productName": "Alphazap",
      "productType": "dinner",
      "qty": 26,
      "price": {
        "currencyCode": "PHP",
        "value": 812
      }
    },
    {
      "img": "https://webbox.imgix.net/images/owvecfmxulwbfvxm/c56a0c0d-8454-431a-9b3e-f420c72e82e3.jpg?auto=format",
      "productId": "72cca4174b74ae82fd6066c3af63b90742bcab37",
      "productName": "Veribet",
      "productType": "room",
      "qty": 56,
      "price": {
        "currencyCode": "PHP",
        "value": 517
      }
    },
    {
      "img": "https://webbox.imgix.net/images/owvecfmxulwbfvxm/7421591e-1ef6-4e85-b93c-94e5a105d39b.jpg?auto=format",
      "productId": "e995e362dac88b9668de3a21f9ac159570c65961",
      "productName": "Opela",
      "productType": "dinner",
      "qty": 77,
      "price": {
        "currencyCode": "PHP",
        "value": 826
      }
    },
    {
      "img": "https://webbox.imgix.net/images/owvecfmxulwbfvxm/c56a0c0d-8454-431a-9b3e-f420c72e82e3.jpg?auto=format",
      "productId": "3659d06b6bbecafb4196f6713264fa39bede5cc3",
      "productName": "Flexidy",
      "productType": "msc",
      "qty": 85,
      "price": {
        "currencyCode": "PHP",
        "value": 111
      }
    },
    {
      "img": "https://webbox.imgix.net/images/owvecfmxulwbfvxm/c56a0c0d-8454-431a-9b3e-f420c72e82e3.jpg?auto=format",
      "productId": "c7e1afce510623695a16c3deb8cca72a79adb97f",
      "productName": "Trippledex",
      "productType": "breakfast",
      "qty": 73,
      "price": {
        "currencyCode": "PHP",
        "value": 256
      }
    },
    {
      "img": "https://webbox.imgix.net/images/owvecfmxulwbfvxm/a92f9ff0-237d-41ea-b48c-58a92f61995e.jpg?auto=format",
      "productId": "3722410dc8d3c76c217863841aca5390198314ef",
      "productName": "Y-Solowarm",
      "productType": "lunch",
      "qty": 80,
      "price": {
        "currencyCode": "PHP",
        "value": 225
      }
    },
    {
      "img": "https://webbox.imgix.net/images/owvecfmxulwbfvxm/a92f9ff0-237d-41ea-b48c-58a92f61995e.jpg?auto=format",
      "productId": "5e2ff0f01caf59f18d593cbcb76fa0bdb2d05a48",
      "productName": "Tempsoft",
      "productType": "lunch",
      "qty": 80,
      "price": {
        "currencyCode": "PHP",
        "value": 358
      }
    },
    {
      "img": "https://webbox.imgix.net/images/owvecfmxulwbfvxm/c56a0c0d-8454-431a-9b3e-f420c72e82e3.jpg?auto=format",
      "productId": "f093c4aacb33a9bae41191755d4dae376f78e6de",
      "productName": "Greenlam",
      "productType": "room",
      "qty": 15,
      "price": {
        "currencyCode": "PHP",
        "value": 746
      }
    },
    {
      "img": "https://webbox.imgix.net/images/owvecfmxulwbfvxm/7421591e-1ef6-4e85-b93c-94e5a105d39b.jpg?auto=format",
      "productId": "bee72416ef7cf2d1ceaa627ccd92bf6a158e0c39",
      "productName": "Veribet",
      "productType": "msc",
      "qty": 39,
      "price": {
        "currencyCode": "PHP",
        "value": 605
      }
    },
    {
      "img": "https://webbox.imgix.net/images/owvecfmxulwbfvxm/a92f9ff0-237d-41ea-b48c-58a92f61995e.jpg?auto=format",
      "productId": "2b287cd0aab34ff5fa959869225f49af5604590a",
      "productName": "Voyatouch",
      "productType": "dinner",
      "qty": 95,
      "price": {
        "currencyCode": "PHP",
        "value": 122
      }
    },
    {
      "img": "https://webbox.imgix.net/images/owvecfmxulwbfvxm/c56a0c0d-8454-431a-9b3e-f420c72e82e3.jpg?auto=format",
      "productId": "465cc723a4779883dedd69343dfce5bdeafb430a",
      "productName": "Tres-Zap",
      "productType": "dinner",
      "qty": 43,
      "price": {
        "currencyCode": "PHP",
        "value": 825
      }
    },
    {
      "img": "https://webbox.imgix.net/images/owvecfmxulwbfvxm/7421591e-1ef6-4e85-b93c-94e5a105d39b.jpg?auto=format",
      "productId": "d24246b7c02e2156b6068ca99861771528704a53",
      "productName": "Keylex",
      "productType": "msc",
      "qty": 88,
      "price": {
        "currencyCode": "PHP",
        "value": 614
      }
    },
    {
      "img": "https://webbox.imgix.net/images/owvecfmxulwbfvxm/c56a0c0d-8454-431a-9b3e-f420c72e82e3.jpg?auto=format",
      "productId": "6e73731a46c3462e071f55db4be49a6cd5664e4c",
      "productName": "Konklab",
      "productType": "lunch",
      "qty": 57,
      "price": {
        "currencyCode": "PHP",
        "value": 751
      }
    },
    {
      "img": "https://webbox.imgix.net/images/owvecfmxulwbfvxm/7421591e-1ef6-4e85-b93c-94e5a105d39b.jpg?auto=format",
      "productId": "542d01e67191aaafc19b13877a422c1105f8a17f",
      "productName": "Voyatouch",
      "productType": "room",
      "qty": 5,
      "price": {
        "currencyCode": "PHP",
        "value": 435
      }
    },
    {
      "img": "https://webbox.imgix.net/images/owvecfmxulwbfvxm/7421591e-1ef6-4e85-b93c-94e5a105d39b.jpg?auto=format",
      "productId": "6538545d3136f36aced8507e2da8bd9be39b8500",
      "productName": "Cardify",
      "productType": "msc",
      "qty": 52,
      "price": {
        "currencyCode": "PHP",
        "value": 960
      }
    },
    {
      "img": "https://webbox.imgix.net/images/owvecfmxulwbfvxm/7421591e-1ef6-4e85-b93c-94e5a105d39b.jpg?auto=format",
      "productId": "c96a340a230e086dd4280710189179c9b99f9ef5",
      "productName": "Greenlam",
      "productType": "dinner",
      "qty": 59,
      "price": {
        "currencyCode": "PHP",
        "value": 634
      }
    },
    {
      "img": "https://webbox.imgix.net/images/owvecfmxulwbfvxm/a92f9ff0-237d-41ea-b48c-58a92f61995e.jpg?auto=format",
      "productId": "ea71d318c6fc422206c1dba31d1dfd1af183c5fe",
      "productName": "Otcom",
      "productType": "room",
      "qty": 29,
      "price": {
        "currencyCode": "PHP",
        "value": 526
      }
    },
    {
      "img": "https://webbox.imgix.net/images/owvecfmxulwbfvxm/c56a0c0d-8454-431a-9b3e-f420c72e82e3.jpg?auto=format",
      "productId": "fc3cdde3d002c322d71086b0c5e96e7bb630b436",
      "productName": "Asoka",
      "productType": "lunch",
      "qty": 32,
      "price": {
        "currencyCode": "PHP",
        "value": 950
      }
    },
    {
      "img": "https://webbox.imgix.net/images/owvecfmxulwbfvxm/c56a0c0d-8454-431a-9b3e-f420c72e82e3.jpg?auto=format",
      "productId": "8ddb24898e3d8655d048c68a87c7f8fb561dd3cf",
      "productName": "Bitchip",
      "productType": "lunch",
      "qty": 2,
      "price": {
        "currencyCode": "PHP",
        "value": 990
      }
    },
    {
      "img": "https://webbox.imgix.net/images/owvecfmxulwbfvxm/7421591e-1ef6-4e85-b93c-94e5a105d39b.jpg?auto=format",
      "productId": "e02e59e2e381e65d5cd0bd76eb9b946ad6ac55bc",
      "productName": "Matsoft",
      "productType": "room",
      "qty": 60,
      "price": {
        "currencyCode": "PHP",
        "value": 482
      }
    },
    {
      "img": "https://webbox.imgix.net/images/owvecfmxulwbfvxm/a92f9ff0-237d-41ea-b48c-58a92f61995e.jpg?auto=format",
      "productId": "3e419d66a195bd06d46b2171e4978b16ccb708f7",
      "productName": "Flowdesk",
      "productType": "lunch",
      "qty": 74,
      "price": {
        "currencyCode": "PHP",
        "value": 851
      }
    },
    {
      "img": "https://webbox.imgix.net/images/owvecfmxulwbfvxm/a92f9ff0-237d-41ea-b48c-58a92f61995e.jpg?auto=format",
      "productId": "a5bb341fc7a64c038ca4ffcea3a7fb3f1fec56cf",
      "productName": "Matsoft",
      "productType": "breakfast",
      "qty": 31,
      "price": {
        "currencyCode": "PHP",
        "value": 287
      }
    },
    {
      "img": "https://webbox.imgix.net/images/owvecfmxulwbfvxm/7421591e-1ef6-4e85-b93c-94e5a105d39b.jpg?auto=format",
      "productId": "caba4fc9e1052737507be41ff9c61ffffa3dc92d",
      "productName": "Hatity",
      "productType": "msc",
      "qty": 27,
      "price": {
        "currencyCode": "PHP",
        "value": 613
      }
    },
    {
      "img": "https://webbox.imgix.net/images/owvecfmxulwbfvxm/7421591e-1ef6-4e85-b93c-94e5a105d39b.jpg?auto=format",
      "productId": "3d2a61f40c4a0065c152fcb81e7cd2b992b224c4",
      "productName": "Zamit",
      "productType": "breakfast",
      "qty": 39,
      "price": {
        "currencyCode": "PHP",
        "value": 738
      }
    },
    {
      "img": "https://webbox.imgix.net/images/owvecfmxulwbfvxm/7421591e-1ef6-4e85-b93c-94e5a105d39b.jpg?auto=format",
      "productId": "fdf1b0cc502e9cff898af6a72751e336862c6953",
      "productName": "Cookley",
      "productType": "lunch",
      "qty": 56,
      "price": {
        "currencyCode": "PHP",
        "value": 412
      }
    },
    {
      "img": "https://webbox.imgix.net/images/owvecfmxulwbfvxm/7421591e-1ef6-4e85-b93c-94e5a105d39b.jpg?auto=format",
      "productId": "8e2eef95cf4cca7a088e2609215068cda0e15e71",
      "productName": "Ronstring",
      "productType": "msc",
      "qty": 4,
      "price": {
        "currencyCode": "PHP",
        "value": 497
      }
    },
    {
      "img": "https://webbox.imgix.net/images/owvecfmxulwbfvxm/a92f9ff0-237d-41ea-b48c-58a92f61995e.jpg?auto=format",
      "productId": "e3630a3cb8f2db9938faeb5a6af4f3111dac3bb4",
      "productName": "Alpha",
      "productType": "dinner",
      "qty": 20,
      "price": {
        "currencyCode": "PHP",
        "value": 361
      }
    },
    {
      "img": "https://webbox.imgix.net/images/owvecfmxulwbfvxm/c56a0c0d-8454-431a-9b3e-f420c72e82e3.jpg?auto=format",
      "productId": "b83b0abbd1e549ba9ae22c14d65481b853a2a274",
      "productName": "Subin",
      "productType": "room",
      "qty": 3,
      "price": {
        "currencyCode": "PHP",
        "value": 739
      }
    },
    {
      "img": "https://webbox.imgix.net/images/owvecfmxulwbfvxm/a92f9ff0-237d-41ea-b48c-58a92f61995e.jpg?auto=format",
      "productId": "f35520812d58be468bdb16c7a61dea528089252e",
      "productName": "Zontrax",
      "productType": "room",
      "qty": 32,
      "price": {
        "currencyCode": "PHP",
        "value": 581
      }
    },
    {
      "img": "https://webbox.imgix.net/images/owvecfmxulwbfvxm/a92f9ff0-237d-41ea-b48c-58a92f61995e.jpg?auto=format",
      "productId": "284f189954bca79486ab1cf716f0bd391a37ffb2",
      "productName": "Konklab",
      "productType": "dinner",
      "qty": 81,
      "price": {
        "currencyCode": "PHP",
        "value": 718
      }
    },
    {
      "img": "https://webbox.imgix.net/images/owvecfmxulwbfvxm/c56a0c0d-8454-431a-9b3e-f420c72e82e3.jpg?auto=format",
      "productId": "9fc5a0c05d4c86c96d99da518367335496584fde",
      "productName": "Zathin",
      "productType": "breakfast",
      "qty": 10,
      "price": {
        "currencyCode": "PHP",
        "value": 635
      }
    },
    {
      "img": "https://webbox.imgix.net/images/owvecfmxulwbfvxm/7421591e-1ef6-4e85-b93c-94e5a105d39b.jpg?auto=format",
      "productId": "7367295dc422eb7d06e6fee42bbdef0e3b3e85c8",
      "productName": "Tres-Zap",
      "productType": "msc",
      "qty": 29,
      "price": {
        "currencyCode": "PHP",
        "value": 163
      }
    },
    {
      "img": "https://webbox.imgix.net/images/owvecfmxulwbfvxm/7421591e-1ef6-4e85-b93c-94e5a105d39b.jpg?auto=format",
      "productId": "8a29d15b021b39f434694c1b54d304ae8bdd8a5c",
      "productName": "It",
      "productType": "room",
      "qty": 87,
      "price": {
        "currencyCode": "PHP",
        "value": 504
      }
    },
    {
      "img": "https://webbox.imgix.net/images/owvecfmxulwbfvxm/c56a0c0d-8454-431a-9b3e-f420c72e82e3.jpg?auto=format",
      "productId": "34fd7a957c25d8da4b33a267d06d4739ebf91930",
      "productName": "Zontrax",
      "productType": "room",
      "qty": 49,
      "price": {
        "currencyCode": "PHP",
        "value": 636
      }
    },
    {
      "img": "https://webbox.imgix.net/images/owvecfmxulwbfvxm/7421591e-1ef6-4e85-b93c-94e5a105d39b.jpg?auto=format",
      "productId": "0fe2a1b7bf0eeecd26ba4aeb6df324fb2c0b1786",
      "productName": "Alpha",
      "productType": "breakfast",
      "qty": 48,
      "price": {
        "currencyCode": "PHP",
        "value": 166
      }
    },
    {
      "img": "https://webbox.imgix.net/images/owvecfmxulwbfvxm/a92f9ff0-237d-41ea-b48c-58a92f61995e.jpg?auto=format",
      "productId": "21873db94ec6e23c2b28bf90808c220175f26523",
      "productName": "Tres-Zap",
      "productType": "lunch",
      "qty": 91,
      "price": {
        "currencyCode": "PHP",
        "value": 313
      }
    },
    {
      "img": "https://webbox.imgix.net/images/owvecfmxulwbfvxm/7421591e-1ef6-4e85-b93c-94e5a105d39b.jpg?auto=format",
      "productId": "c45891bb9ececfec2643bdb9c926556f1a808aff",
      "productName": "Pannier",
      "productType": "dinner",
      "qty": 69,
      "price": {
        "currencyCode": "PHP",
        "value": 136
      }
    },
    {
      "img": "https://webbox.imgix.net/images/owvecfmxulwbfvxm/a92f9ff0-237d-41ea-b48c-58a92f61995e.jpg?auto=format",
      "productId": "27c3d8171520223223b19419f94c997d4bebc3b4",
      "productName": "Wrapsafe",
      "productType": "dinner",
      "qty": 84,
      "price": {
        "currencyCode": "PHP",
        "value": 234
      }
    },
    {
      "img": "https://webbox.imgix.net/images/owvecfmxulwbfvxm/7421591e-1ef6-4e85-b93c-94e5a105d39b.jpg?auto=format",
      "productId": "62bfd3f879c2cdffb9ee4363f1af5affdf963c95",
      "productName": "Fixflex",
      "productType": "msc",
      "qty": 51,
      "price": {
        "currencyCode": "PHP",
        "value": 845
      }
    },
    {
      "img": "https://webbox.imgix.net/images/owvecfmxulwbfvxm/c56a0c0d-8454-431a-9b3e-f420c72e82e3.jpg?auto=format",
      "productId": "e720bfbb371db82d4adf429aa52025841ec9eb6e",
      "productName": "Andalax",
      "productType": "breakfast",
      "qty": 30,
      "price": {
        "currencyCode": "PHP",
        "value": 730
      }
    },
    {
      "img": "https://webbox.imgix.net/images/owvecfmxulwbfvxm/c56a0c0d-8454-431a-9b3e-f420c72e82e3.jpg?auto=format",
      "productId": "f0b6f04ec060b55359aa824438614ae26922cc1c",
      "productName": "Tempsoft",
      "productType": "dinner",
      "qty": 19,
      "price": {
        "currencyCode": "PHP",
        "value": 710
      }
    },
    {
      "img": "https://webbox.imgix.net/images/owvecfmxulwbfvxm/c56a0c0d-8454-431a-9b3e-f420c72e82e3.jpg?auto=format",
      "productId": "37489145dfc6240e20df92410346ea5f35b079bd",
      "productName": "Redhold",
      "productType": "dinner",
      "qty": 93,
      "price": {
        "currencyCode": "PHP",
        "value": 49
      }
    },
    {
      "img": "https://webbox.imgix.net/images/owvecfmxulwbfvxm/7421591e-1ef6-4e85-b93c-94e5a105d39b.jpg?auto=format",
      "productId": "744b712b66482bb877495a4b573b52926ef24aa0",
      "productName": "Transcof",
      "productType": "msc",
      "qty": 93,
      "price": {
        "currencyCode": "PHP",
        "value": 588
      }
    },
    {
      "img": "https://webbox.imgix.net/images/owvecfmxulwbfvxm/7421591e-1ef6-4e85-b93c-94e5a105d39b.jpg?auto=format",
      "productId": "32746d3b8b82adeb553e6b6a6135ebf539e41332",
      "productName": "Mat Lam Tam",
      "productType": "breakfast",
      "qty": 69,
      "price": {
        "currencyCode": "PHP",
        "value": 885
      }
    },
    {
      "img": "https://webbox.imgix.net/images/owvecfmxulwbfvxm/a92f9ff0-237d-41ea-b48c-58a92f61995e.jpg?auto=format",
      "productId": "2d926357e3375739293f0ceb37f27d235bf26973",
      "productName": "Tampflex",
      "productType": "lunch",
      "qty": 20,
      "price": {
        "currencyCode": "PHP",
        "value": 930
      }
    },
    {
      "img": "https://webbox.imgix.net/images/owvecfmxulwbfvxm/a92f9ff0-237d-41ea-b48c-58a92f61995e.jpg?auto=format",
      "productId": "94d35e275a9f75ae5f5b41dd80391535e8041414",
      "productName": "Tin",
      "productType": "room",
      "qty": 75,
      "price": {
        "currencyCode": "PHP",
        "value": 443
      }
    },
    {
      "img": "https://webbox.imgix.net/images/owvecfmxulwbfvxm/c56a0c0d-8454-431a-9b3e-f420c72e82e3.jpg?auto=format",
      "productId": "bb22f486e485ef78f597213bb469e9757c21dbbd",
      "productName": "Kanlam",
      "productType": "breakfast",
      "qty": 89,
      "price": {
        "currencyCode": "PHP",
        "value": 647
      }
    },
    {
      "img": "https://webbox.imgix.net/images/owvecfmxulwbfvxm/c56a0c0d-8454-431a-9b3e-f420c72e82e3.jpg?auto=format",
      "productId": "a14d6b8291da8b7dad75d9e63c1c1c4c372fc04e",
      "productName": "Mat Lam Tam",
      "productType": "msc",
      "qty": 4,
      "price": {
        "currencyCode": "PHP",
        "value": 113
      }
    },
    {
      "img": "https://webbox.imgix.net/images/owvecfmxulwbfvxm/a92f9ff0-237d-41ea-b48c-58a92f61995e.jpg?auto=format",
      "productId": "fb5c74c2ff9ed580a969a739440507e2b4f98b2c",
      "productName": "Holdlamis",
      "productType": "msc",
      "qty": 61,
      "price": {
        "currencyCode": "PHP",
        "value": 869
      }
    },
    {
      "img": "https://webbox.imgix.net/images/owvecfmxulwbfvxm/a92f9ff0-237d-41ea-b48c-58a92f61995e.jpg?auto=format",
      "productId": "a99640ff447b948eaeef167ab0007fe1699f749a",
      "productName": "Toughjoyfax",
      "productType": "lunch",
      "qty": 87,
      "price": {
        "currencyCode": "PHP",
        "value": 552
      }
    },
    {
      "img": "https://webbox.imgix.net/images/owvecfmxulwbfvxm/7421591e-1ef6-4e85-b93c-94e5a105d39b.jpg?auto=format",
      "productId": "346ac55981fa5605ac8d65d84abad966d2549b2c",
      "productName": "Hatity",
      "productType": "lunch",
      "qty": 51,
      "price": {
        "currencyCode": "PHP",
        "value": 5
      }
    },
    {
      "img": "https://webbox.imgix.net/images/owvecfmxulwbfvxm/7421591e-1ef6-4e85-b93c-94e5a105d39b.jpg?auto=format",
      "productId": "cea961b2e29889a1a2cfbaf953b444b097742e23",
      "productName": "Job",
      "productType": "msc",
      "qty": 60,
      "price": {
        "currencyCode": "PHP",
        "value": 480
      }
    },
    {
      "img": "https://webbox.imgix.net/images/owvecfmxulwbfvxm/c56a0c0d-8454-431a-9b3e-f420c72e82e3.jpg?auto=format",
      "productId": "25614235fe06dd605aaf9d8ec312de437adddd6f",
      "productName": "Zamit",
      "productType": "room",
      "qty": 44,
      "price": {
        "currencyCode": "PHP",
        "value": 349
      }
    },
    {
      "img": "https://webbox.imgix.net/images/owvecfmxulwbfvxm/c56a0c0d-8454-431a-9b3e-f420c72e82e3.jpg?auto=format",
      "productId": "b1b1f6d2535b3f13d1f2d464dc1ef00186dc321d",
      "productName": "Otcom",
      "productType": "dinner",
      "qty": 60,
      "price": {
        "currencyCode": "PHP",
        "value": 694
      }
    },
    {
      "img": "https://webbox.imgix.net/images/owvecfmxulwbfvxm/c56a0c0d-8454-431a-9b3e-f420c72e82e3.jpg?auto=format",
      "productId": "e81c819a3464c9b0a401e1e5a0f4e75e4a107836",
      "productName": "Matsoft",
      "productType": "room",
      "qty": 31,
      "price": {
        "currencyCode": "PHP",
        "value": 337
      }
    },
    {
      "img": "https://webbox.imgix.net/images/owvecfmxulwbfvxm/c56a0c0d-8454-431a-9b3e-f420c72e82e3.jpg?auto=format",
      "productId": "5cbba4880219797363295291a1665e89df45521a",
      "productName": "Flowdesk",
      "productType": "dinner",
      "qty": 97,
      "price": {
        "currencyCode": "PHP",
        "value": 416
      }
    },
    {
      "img": "https://webbox.imgix.net/images/owvecfmxulwbfvxm/a92f9ff0-237d-41ea-b48c-58a92f61995e.jpg?auto=format",
      "productId": "53ccc67c3d89e311b8bc1e941316d257cc8d821c",
      "productName": "Flowdesk",
      "productType": "dinner",
      "qty": 26,
      "price": {
        "currencyCode": "PHP",
        "value": 107
      }
    },
    {
      "img": "https://webbox.imgix.net/images/owvecfmxulwbfvxm/c56a0c0d-8454-431a-9b3e-f420c72e82e3.jpg?auto=format",
      "productId": "70da12ab094792a9ec7dbd2a986d8983fcf3765e",
      "productName": "Ventosanzap",
      "productType": "msc",
      "qty": 19,
      "price": {
        "currencyCode": "PHP",
        "value": 693
      }
    },
    {
      "img": "https://webbox.imgix.net/images/owvecfmxulwbfvxm/7421591e-1ef6-4e85-b93c-94e5a105d39b.jpg?auto=format",
      "productId": "1380799627e0ee002315da3ca16a6fa11f9441f0",
      "productName": "Lotlux",
      "productType": "room",
      "qty": 23,
      "price": {
        "currencyCode": "PHP",
        "value": 625
      }
    },
    {
      "img": "https://webbox.imgix.net/images/owvecfmxulwbfvxm/a92f9ff0-237d-41ea-b48c-58a92f61995e.jpg?auto=format",
      "productId": "2d699aa54d29d8fe319667da08f3b2fb365cb556",
      "productName": "Opela",
      "productType": "room",
      "qty": 9,
      "price": {
        "currencyCode": "PHP",
        "value": 364
      }
    },
    {
      "img": "https://webbox.imgix.net/images/owvecfmxulwbfvxm/a92f9ff0-237d-41ea-b48c-58a92f61995e.jpg?auto=format",
      "productId": "402acb2c11f5a571db152d15cffa40f04718d48c",
      "productName": "Sonair",
      "productType": "lunch",
      "qty": 79,
      "price": {
        "currencyCode": "PHP",
        "value": 50
      }
    },
    {
      "img": "https://webbox.imgix.net/images/owvecfmxulwbfvxm/a92f9ff0-237d-41ea-b48c-58a92f61995e.jpg?auto=format",
      "productId": "791a1baf53627166f51a8bf099b0c99897760351",
      "productName": "Fixflex",
      "productType": "msc",
      "qty": 69,
      "price": {
        "currencyCode": "PHP",
        "value": 723
      }
    },
    {
      "img": "https://webbox.imgix.net/images/owvecfmxulwbfvxm/c56a0c0d-8454-431a-9b3e-f420c72e82e3.jpg?auto=format",
      "productId": "8734cd03f7fcb0fa4a0927b39adf7b3c32b7b941",
      "productName": "Prodder",
      "productType": "dinner",
      "qty": 76,
      "price": {
        "currencyCode": "PHP",
        "value": 59
      }
    },
    {
      "img": "https://webbox.imgix.net/images/owvecfmxulwbfvxm/c56a0c0d-8454-431a-9b3e-f420c72e82e3.jpg?auto=format",
      "productId": "d32444024dc99c7881d5200aff1d42c842e3d101",
      "productName": "Bytecard",
      "productType": "lunch",
      "qty": 78,
      "price": {
        "currencyCode": "PHP",
        "value": 255
      }
    },
    {
      "img": "https://webbox.imgix.net/images/owvecfmxulwbfvxm/7421591e-1ef6-4e85-b93c-94e5a105d39b.jpg?auto=format",
      "productId": "1087ef0648cc114fad4646f443f2c5f4f2aecba1",
      "productName": "Flowdesk",
      "productType": "breakfast",
      "qty": 98,
      "price": {
        "currencyCode": "PHP",
        "value": 967
      }
    },
    {
      "img": "https://webbox.imgix.net/images/owvecfmxulwbfvxm/a92f9ff0-237d-41ea-b48c-58a92f61995e.jpg?auto=format",
      "productId": "8b73523184b53c86b38723c59dd68b8d8c973f40",
      "productName": "Regrant",
      "productType": "dinner",
      "qty": 32,
      "price": {
        "currencyCode": "PHP",
        "value": 80
      }
    },
    {
      "img": "https://webbox.imgix.net/images/owvecfmxulwbfvxm/c56a0c0d-8454-431a-9b3e-f420c72e82e3.jpg?auto=format",
      "productId": "a42c3df884ab4b6c94898fe1706ebec6073e2b61",
      "productName": "Konklab",
      "productType": "dinner",
      "qty": 100,
      "price": {
        "currencyCode": "PHP",
        "value": 63
      }
    },
    {
      "img": "https://webbox.imgix.net/images/owvecfmxulwbfvxm/c56a0c0d-8454-431a-9b3e-f420c72e82e3.jpg?auto=format",
      "productId": "16b0793cb2cc8a5fe4901e4fd48f65fad72e4600",
      "productName": "Sonsing",
      "productType": "breakfast",
      "qty": 70,
      "price": {
        "currencyCode": "PHP",
        "value": 204
      }
    },
    {
      "img": "https://webbox.imgix.net/images/owvecfmxulwbfvxm/7421591e-1ef6-4e85-b93c-94e5a105d39b.jpg?auto=format",
      "productId": "4779cd3261ea7ef978878e74d58d9edfe00ba30a",
      "productName": "Zamit",
      "productType": "lunch",
      "qty": 97,
      "price": {
        "currencyCode": "PHP",
        "value": 54
      }
    },
    {
      "img": "https://webbox.imgix.net/images/owvecfmxulwbfvxm/a92f9ff0-237d-41ea-b48c-58a92f61995e.jpg?auto=format",
      "productId": "4704b082e470fdb05db1a2b92c5a9438a15a544b",
      "productName": "Cardguard",
      "productType": "lunch",
      "qty": 74,
      "price": {
        "currencyCode": "PHP",
        "value": 144
      }
    },
    {
      "img": "https://webbox.imgix.net/images/owvecfmxulwbfvxm/c56a0c0d-8454-431a-9b3e-f420c72e82e3.jpg?auto=format",
      "productId": "ffc168fd48f0129db5aaebbd4b10e31ce8ac2613",
      "productName": "Asoka",
      "productType": "lunch",
      "qty": 67,
      "price": {
        "currencyCode": "PHP",
        "value": 729
      }
    },
    {
      "img": "https://webbox.imgix.net/images/owvecfmxulwbfvxm/c56a0c0d-8454-431a-9b3e-f420c72e82e3.jpg?auto=format",
      "productId": "88a7dba975fb44a1baa79fd7bd8df936002bd055",
      "productName": "Opela",
      "productType": "room",
      "qty": 15,
      "price": {
        "currencyCode": "PHP",
        "value": 806
      }
    },
    {
      "img": "https://webbox.imgix.net/images/owvecfmxulwbfvxm/c56a0c0d-8454-431a-9b3e-f420c72e82e3.jpg?auto=format",
      "productId": "951b4596555fb6db209b25b75deae84f44428900",
      "productName": "Tresom",
      "productType": "breakfast",
      "qty": 57,
      "price": {
        "currencyCode": "PHP",
        "value": 41
      }
    },
    {
      "img": "https://webbox.imgix.net/images/owvecfmxulwbfvxm/7421591e-1ef6-4e85-b93c-94e5a105d39b.jpg?auto=format",
      "productId": "c5077894b13a2276b78e431b50e4ad558417ef0e",
      "productName": "Hatity",
      "productType": "msc",
      "qty": 10,
      "price": {
        "currencyCode": "PHP",
        "value": 152
      }
    },
    {
      "img": "https://webbox.imgix.net/images/owvecfmxulwbfvxm/a92f9ff0-237d-41ea-b48c-58a92f61995e.jpg?auto=format",
      "productId": "b97278e3502f741095e8f876701f5f1f1f7d420d",
      "productName": "Stim",
      "productType": "breakfast",
      "qty": 93,
      "price": {
        "currencyCode": "PHP",
        "value": 932
      }
    },
    {
      "img": "https://webbox.imgix.net/images/owvecfmxulwbfvxm/c56a0c0d-8454-431a-9b3e-f420c72e82e3.jpg?auto=format",
      "productId": "ca86dd2c94693447dae765cf01c504d966dbb724",
      "productName": "Rank",
      "productType": "msc",
      "qty": 34,
      "price": {
        "currencyCode": "PHP",
        "value": 553
      }
    },
    {
      "img": "https://webbox.imgix.net/images/owvecfmxulwbfvxm/c56a0c0d-8454-431a-9b3e-f420c72e82e3.jpg?auto=format",
      "productId": "723fb3ed57d8a6a062da2596b228f20e82c76a0c",
      "productName": "Holdlamis",
      "productType": "room",
      "qty": 66,
      "price": {
        "currencyCode": "PHP",
        "value": 687
      }
    },
    {
      "img": "https://webbox.imgix.net/images/owvecfmxulwbfvxm/c56a0c0d-8454-431a-9b3e-f420c72e82e3.jpg?auto=format",
      "productId": "64bc87e899ffb09194dc1082efeb11e751f73d4f",
      "productName": "Andalax",
      "productType": "msc",
      "qty": 63,
      "price": {
        "currencyCode": "PHP",
        "value": 776
      }
    },
    {
      "img": "https://webbox.imgix.net/images/owvecfmxulwbfvxm/a92f9ff0-237d-41ea-b48c-58a92f61995e.jpg?auto=format",
      "productId": "d7a9d68e15e593aaf65e894127e5fecdba85c8d8",
      "productName": "Bytecard",
      "productType": "room",
      "qty": 83,
      "price": {
        "currencyCode": "PHP",
        "value": 332
      }
    },
    {
      "img": "https://webbox.imgix.net/images/owvecfmxulwbfvxm/7421591e-1ef6-4e85-b93c-94e5a105d39b.jpg?auto=format",
      "productId": "769d13a2e4ebc9ad5d31583984721f792e64240a",
      "productName": "Mat Lam Tam",
      "productType": "breakfast",
      "qty": 48,
      "price": {
        "currencyCode": "PHP",
        "value": 994
      }
    },
    {
      "img": "https://webbox.imgix.net/images/owvecfmxulwbfvxm/7421591e-1ef6-4e85-b93c-94e5a105d39b.jpg?auto=format",
      "productId": "1c2d075a9aca14325ba39f034143425853a6a946",
      "productName": "Fintone",
      "productType": "room",
      "qty": 67,
      "price": {
        "currencyCode": "PHP",
        "value": 566
      }
    },
    {
      "img": "https://webbox.imgix.net/images/owvecfmxulwbfvxm/7421591e-1ef6-4e85-b93c-94e5a105d39b.jpg?auto=format",
      "productId": "9ad9f7e0fe6fea2b4407dc6a611dda9e939186e4",
      "productName": "Stronghold",
      "productType": "dinner",
      "qty": 76,
      "price": {
        "currencyCode": "PHP",
        "value": 692
      }
    },
    {
      "img": "https://webbox.imgix.net/images/owvecfmxulwbfvxm/c56a0c0d-8454-431a-9b3e-f420c72e82e3.jpg?auto=format",
      "productId": "5eb3df40548d98c74c6395b10f92afaf2c5f50a9",
      "productName": "Bitchip",
      "productType": "dinner",
      "qty": 2,
      "price": {
        "currencyCode": "PHP",
        "value": 831
      }
    },
    {
      "img": "https://webbox.imgix.net/images/owvecfmxulwbfvxm/c56a0c0d-8454-431a-9b3e-f420c72e82e3.jpg?auto=format",
      "productId": "0a26834e834cc3b130764c81034bf846a4c1c680",
      "productName": "Viva",
      "productType": "breakfast",
      "qty": 80,
      "price": {
        "currencyCode": "PHP",
        "value": 763
      }
    },
    {
      "img": "https://webbox.imgix.net/images/owvecfmxulwbfvxm/7421591e-1ef6-4e85-b93c-94e5a105d39b.jpg?auto=format",
      "productId": "b0bd0e8978412ee59695384a39717166e17cdee9",
      "productName": "Daltfresh",
      "productType": "dinner",
      "qty": 27,
      "price": {
        "currencyCode": "PHP",
        "value": 947
      }
    },
    {
      "img": "https://webbox.imgix.net/images/owvecfmxulwbfvxm/7421591e-1ef6-4e85-b93c-94e5a105d39b.jpg?auto=format",
      "productId": "57e2c789dcda88db130f735f8457f62db216b4d5",
      "productName": "Biodex",
      "productType": "lunch",
      "qty": 58,
      "price": {
        "currencyCode": "PHP",
        "value": 554
      }
    },
    {
      "img": "https://webbox.imgix.net/images/owvecfmxulwbfvxm/c56a0c0d-8454-431a-9b3e-f420c72e82e3.jpg?auto=format",
      "productId": "74f5415248e9bc69f6b760e4ac5e8c1379e4f277",
      "productName": "Opela",
      "productType": "breakfast",
      "qty": 68,
      "price": {
        "currencyCode": "PHP",
        "value": 672
      }
    },
    {
      "img": "https://webbox.imgix.net/images/owvecfmxulwbfvxm/a92f9ff0-237d-41ea-b48c-58a92f61995e.jpg?auto=format",
      "productId": "0cf1280bae9639e3f2747f99564c7a0e29d35596",
      "productName": "Span",
      "productType": "dinner",
      "qty": 60,
      "price": {
        "currencyCode": "PHP",
        "value": 816
      }
    },
    {
      "img": "https://webbox.imgix.net/images/owvecfmxulwbfvxm/7421591e-1ef6-4e85-b93c-94e5a105d39b.jpg?auto=format",
      "productId": "cf43c7595f904c71e3fa72a19b816115eeee60b1",
      "productName": "Temp",
      "productType": "breakfast",
      "qty": 59,
      "price": {
        "currencyCode": "PHP",
        "value": 435
      }
    },
    {
      "img": "https://webbox.imgix.net/images/owvecfmxulwbfvxm/c56a0c0d-8454-431a-9b3e-f420c72e82e3.jpg?auto=format",
      "productId": "9944fedffad0e7592bd18675be6c97517b383793",
      "productName": "Temp",
      "productType": "breakfast",
      "qty": 17,
      "price": {
        "currencyCode": "PHP",
        "value": 644
      }
    },
    {
      "img": "https://webbox.imgix.net/images/owvecfmxulwbfvxm/7421591e-1ef6-4e85-b93c-94e5a105d39b.jpg?auto=format",
      "productId": "0cdbe45cdae97840b944adbb7d028e03e1bfc91f",
      "productName": "Duobam",
      "productType": "lunch",
      "qty": 9,
      "price": {
        "currencyCode": "PHP",
        "value": 518
      }
    },
    {
      "img": "https://webbox.imgix.net/images/owvecfmxulwbfvxm/a92f9ff0-237d-41ea-b48c-58a92f61995e.jpg?auto=format",
      "productId": "a954c437d7dada70257af8a7f7d6828c097ffdb9",
      "productName": "It",
      "productType": "breakfast",
      "qty": 82,
      "price": {
        "currencyCode": "PHP",
        "value": 438
      }
    },
    {
      "img": "https://webbox.imgix.net/images/owvecfmxulwbfvxm/a92f9ff0-237d-41ea-b48c-58a92f61995e.jpg?auto=format",
      "productId": "f6dfe8f67dd7c2045f28cb534a2f2a5cf5d5062e",
      "productName": "Tres-Zap",
      "productType": "room",
      "qty": 64,
      "price": {
        "currencyCode": "PHP",
        "value": 368
      }
    },
    {
      "img": "https://webbox.imgix.net/images/owvecfmxulwbfvxm/c56a0c0d-8454-431a-9b3e-f420c72e82e3.jpg?auto=format",
      "productId": "cc66f1499af0f6a002a14eb7c896f16dd08ec563",
      "productName": "Holdlamis",
      "productType": "room",
      "qty": 5,
      "price": {
        "currencyCode": "PHP",
        "value": 595
      }
    },
    {
      "img": "https://webbox.imgix.net/images/owvecfmxulwbfvxm/c56a0c0d-8454-431a-9b3e-f420c72e82e3.jpg?auto=format",
      "productId": "6ed62a56fe1203b8451f0185e40ef9e24d56306c",
      "productName": "Keylex",
      "productType": "dinner",
      "qty": 55,
      "price": {
        "currencyCode": "PHP",
        "value": 193
      }
    },
    {
      "img": "https://webbox.imgix.net/images/owvecfmxulwbfvxm/7421591e-1ef6-4e85-b93c-94e5a105d39b.jpg?auto=format",
      "productId": "00fab7dd5594f0235cce22322cf1643e592680e4",
      "productName": "Job",
      "productType": "dinner",
      "qty": 43,
      "price": {
        "currencyCode": "PHP",
        "value": 632
      }
    },
    {
      "img": "https://webbox.imgix.net/images/owvecfmxulwbfvxm/c56a0c0d-8454-431a-9b3e-f420c72e82e3.jpg?auto=format",
      "productId": "0125d6df1c39466a7db9cefbd90fd23c69e5f1a4",
      "productName": "Latlux",
      "productType": "dinner",
      "qty": 67,
      "price": {
        "currencyCode": "PHP",
        "value": 512
      }
    },
    {
      "img": "https://webbox.imgix.net/images/owvecfmxulwbfvxm/7421591e-1ef6-4e85-b93c-94e5a105d39b.jpg?auto=format",
      "productId": "4f9d2d998c4fa544f4753ebce417ce26c7f094ef",
      "productName": "Namfix",
      "productType": "room",
      "qty": 80,
      "price": {
        "currencyCode": "PHP",
        "value": 101
      }
    },
    {
      "img": "https://webbox.imgix.net/images/owvecfmxulwbfvxm/7421591e-1ef6-4e85-b93c-94e5a105d39b.jpg?auto=format",
      "productId": "87eb733ae4d77073e97d5d9b438b3762bd08af48",
      "productName": "Hatity",
      "productType": "msc",
      "qty": 24,
      "price": {
        "currencyCode": "PHP",
        "value": 894
      }
    },
    {
      "img": "https://webbox.imgix.net/images/owvecfmxulwbfvxm/a92f9ff0-237d-41ea-b48c-58a92f61995e.jpg?auto=format",
      "productId": "6131dbc84ff0479c35cc43249bd4dff3816c7c77",
      "productName": "Y-Solowarm",
      "productType": "lunch",
      "qty": 59,
      "price": {
        "currencyCode": "PHP",
        "value": 256
      }
    },
    {
      "img": "https://webbox.imgix.net/images/owvecfmxulwbfvxm/7421591e-1ef6-4e85-b93c-94e5a105d39b.jpg?auto=format",
      "productId": "52a6d3533c9228b7742cfec620ac62eaf2a00c79",
      "productName": "Regrant",
      "productType": "breakfast",
      "qty": 75,
      "price": {
        "currencyCode": "PHP",
        "value": 151
      }
    },
    {
      "img": "https://webbox.imgix.net/images/owvecfmxulwbfvxm/c56a0c0d-8454-431a-9b3e-f420c72e82e3.jpg?auto=format",
      "productId": "5602d4890382ce54bd2ec7716d2d6efe756ac10f",
      "productName": "Bitchip",
      "productType": "lunch",
      "qty": 15,
      "price": {
        "currencyCode": "PHP",
        "value": 446
      }
    },
    {
      "img": "https://webbox.imgix.net/images/owvecfmxulwbfvxm/7421591e-1ef6-4e85-b93c-94e5a105d39b.jpg?auto=format",
      "productId": "88e52bb886a81e5efbffce5ff9ae5c9c3a7a9ae5",
      "productName": "Overhold",
      "productType": "dinner",
      "qty": 4,
      "price": {
        "currencyCode": "PHP",
        "value": 938
      }
    },
    {
      "img": "https://webbox.imgix.net/images/owvecfmxulwbfvxm/7421591e-1ef6-4e85-b93c-94e5a105d39b.jpg?auto=format",
      "productId": "3b046341a75f1707e797abfa60f439358b0c746b",
      "productName": "Flowdesk",
      "productType": "msc",
      "qty": 73,
      "price": {
        "currencyCode": "PHP",
        "value": 580
      }
    },
    {
      "img": "https://webbox.imgix.net/images/owvecfmxulwbfvxm/c56a0c0d-8454-431a-9b3e-f420c72e82e3.jpg?auto=format",
      "productId": "007f501db755e81be45a4133ba616ecc60204bb3",
      "productName": "Regrant",
      "productType": "lunch",
      "qty": 27,
      "price": {
        "currencyCode": "PHP",
        "value": 549
      }
    },
    {
      "img": "https://webbox.imgix.net/images/owvecfmxulwbfvxm/7421591e-1ef6-4e85-b93c-94e5a105d39b.jpg?auto=format",
      "productId": "f0fb9be10b4baf728f94c394021cc75e618e00d0",
      "productName": "Tres-Zap",
      "productType": "room",
      "qty": 43,
      "price": {
        "currencyCode": "PHP",
        "value": 519
      }
    },
    {
      "img": "https://webbox.imgix.net/images/owvecfmxulwbfvxm/c56a0c0d-8454-431a-9b3e-f420c72e82e3.jpg?auto=format",
      "productId": "7526c267dfc1af7dadb4d9a1f422ef284dfabf88",
      "productName": "Holdlamis",
      "productType": "msc",
      "qty": 92,
      "price": {
        "currencyCode": "PHP",
        "value": 231
      }
    },
    {
      "img": "https://webbox.imgix.net/images/owvecfmxulwbfvxm/a92f9ff0-237d-41ea-b48c-58a92f61995e.jpg?auto=format",
      "productId": "807e965cfdfb11f5540564ed4e4b0976bb586b3d",
      "productName": "Bitchip",
      "productType": "room",
      "qty": 65,
      "price": {
        "currencyCode": "PHP",
        "value": 938
      }
    },
    {
      "img": "https://webbox.imgix.net/images/owvecfmxulwbfvxm/c56a0c0d-8454-431a-9b3e-f420c72e82e3.jpg?auto=format",
      "productId": "312e1c31b38ffd568a74f713b8b61e6b19c80a1d",
      "productName": "Biodex",
      "productType": "breakfast",
      "qty": 85,
      "price": {
        "currencyCode": "PHP",
        "value": 473
      }
    },
    {
      "img": "https://webbox.imgix.net/images/owvecfmxulwbfvxm/a92f9ff0-237d-41ea-b48c-58a92f61995e.jpg?auto=format",
      "productId": "6e2a5020e1342f7cc5258b10e647c86d47179115",
      "productName": "Bitchip",
      "productType": "lunch",
      "qty": 72,
      "price": {
        "currencyCode": "PHP",
        "value": 460
      }
    },
    {
      "img": "https://webbox.imgix.net/images/owvecfmxulwbfvxm/c56a0c0d-8454-431a-9b3e-f420c72e82e3.jpg?auto=format",
      "productId": "4ef2ebcaec16cc7e2835e598cbff398a7d72c438",
      "productName": "Daltfresh",
      "productType": "breakfast",
      "qty": 96,
      "price": {
        "currencyCode": "PHP",
        "value": 204
      }
    },
    {
      "img": "https://webbox.imgix.net/images/owvecfmxulwbfvxm/7421591e-1ef6-4e85-b93c-94e5a105d39b.jpg?auto=format",
      "productId": "3b7dc20727499cd3c8bbdff3734db1e2b8df8d9d",
      "productName": "Redhold",
      "productType": "msc",
      "qty": 46,
      "price": {
        "currencyCode": "PHP",
        "value": 867
      }
    },
    {
      "img": "https://webbox.imgix.net/images/owvecfmxulwbfvxm/7421591e-1ef6-4e85-b93c-94e5a105d39b.jpg?auto=format",
      "productId": "0a1196af052f42a73147cc125dfa4e89afb2a5c3",
      "productName": "Bamity",
      "productType": "dinner",
      "qty": 25,
      "price": {
        "currencyCode": "PHP",
        "value": 222
      }
    },
    {
      "img": "https://webbox.imgix.net/images/owvecfmxulwbfvxm/7421591e-1ef6-4e85-b93c-94e5a105d39b.jpg?auto=format",
      "productId": "39e19528940107cbb13f36fb4b029e0f83e1f5a6",
      "productName": "Namfix",
      "productType": "room",
      "qty": 21,
      "price": {
        "currencyCode": "PHP",
        "value": 147
      }
    },
    {
      "img": "https://webbox.imgix.net/images/owvecfmxulwbfvxm/7421591e-1ef6-4e85-b93c-94e5a105d39b.jpg?auto=format",
      "productId": "7e51b15bdce9d4daf373c3d4e598bc54e590c1d2",
      "productName": "Solarbreeze",
      "productType": "breakfast",
      "qty": 31,
      "price": {
        "currencyCode": "PHP",
        "value": 699
      }
    },
    {
      "img": "https://webbox.imgix.net/images/owvecfmxulwbfvxm/a92f9ff0-237d-41ea-b48c-58a92f61995e.jpg?auto=format",
      "productId": "af07e2380ee6d3f33a35628d8a756a3d2512a676",
      "productName": "Mat Lam Tam",
      "productType": "dinner",
      "qty": 32,
      "price": {
        "currencyCode": "PHP",
        "value": 752
      }
    },
    {
      "img": "https://webbox.imgix.net/images/owvecfmxulwbfvxm/7421591e-1ef6-4e85-b93c-94e5a105d39b.jpg?auto=format",
      "productId": "f7aac61d93401aa75874ae52babdecccc2022d59",
      "productName": "Veribet",
      "productType": "lunch",
      "qty": 26,
      "price": {
        "currencyCode": "PHP",
        "value": 889
      }
    },
    {
      "img": "https://webbox.imgix.net/images/owvecfmxulwbfvxm/c56a0c0d-8454-431a-9b3e-f420c72e82e3.jpg?auto=format",
      "productId": "65f0217f989ef8e756f7a22360669a9fcc0b18a2",
      "productName": "Tin",
      "productType": "lunch",
      "qty": 98,
      "price": {
        "currencyCode": "PHP",
        "value": 912
      }
    },
    {
      "img": "https://webbox.imgix.net/images/owvecfmxulwbfvxm/7421591e-1ef6-4e85-b93c-94e5a105d39b.jpg?auto=format",
      "productId": "bba8a1921b427dd376990638ba857d55679afbb7",
      "productName": "Tempsoft",
      "productType": "breakfast",
      "qty": 2,
      "price": {
        "currencyCode": "PHP",
        "value": 538
      }
    },
    {
      "img": "https://webbox.imgix.net/images/owvecfmxulwbfvxm/7421591e-1ef6-4e85-b93c-94e5a105d39b.jpg?auto=format",
      "productId": "f7f534a83373d3b239296005b59d872825b04eb2",
      "productName": "Greenlam",
      "productType": "lunch",
      "qty": 87,
      "price": {
        "currencyCode": "PHP",
        "value": 7
      }
    },
    {
      "img": "https://webbox.imgix.net/images/owvecfmxulwbfvxm/7421591e-1ef6-4e85-b93c-94e5a105d39b.jpg?auto=format",
      "productId": "b2a36dea265e3fb918343428791cb419f8dd4fb5",
      "productName": "Tresom",
      "productType": "breakfast",
      "qty": 80,
      "price": {
        "currencyCode": "PHP",
        "value": 913
      }
    },
    {
      "img": "https://webbox.imgix.net/images/owvecfmxulwbfvxm/c56a0c0d-8454-431a-9b3e-f420c72e82e3.jpg?auto=format",
      "productId": "0e27a209b398dd31e048bca777705f63e1f858cb",
      "productName": "Stronghold",
      "productType": "lunch",
      "qty": 60,
      "price": {
        "currencyCode": "PHP",
        "value": 428
      }
    },
    {
      "img": "https://webbox.imgix.net/images/owvecfmxulwbfvxm/c56a0c0d-8454-431a-9b3e-f420c72e82e3.jpg?auto=format",
      "productId": "990b74d42994745f1c40b662bc5c8eea8b384938",
      "productName": "Opela",
      "productType": "lunch",
      "qty": 70,
      "price": {
        "currencyCode": "PHP",
        "value": 812
      }
    },
    {
      "img": "https://webbox.imgix.net/images/owvecfmxulwbfvxm/c56a0c0d-8454-431a-9b3e-f420c72e82e3.jpg?auto=format",
      "productId": "97015806a6eaf49c9dccf5203aed7a718f159958",
      "productName": "Greenlam",
      "productType": "dinner",
      "qty": 16,
      "price": {
        "currencyCode": "PHP",
        "value": 847
      }
    },
    {
      "img": "https://webbox.imgix.net/images/owvecfmxulwbfvxm/a92f9ff0-237d-41ea-b48c-58a92f61995e.jpg?auto=format",
      "productId": "be03a5d42ff758344c3a8bd591554a2a6580e9bc",
      "productName": "Hatity",
      "productType": "dinner",
      "qty": 54,
      "price": {
        "currencyCode": "PHP",
        "value": 930
      }
    },
    {
      "img": "https://webbox.imgix.net/images/owvecfmxulwbfvxm/a92f9ff0-237d-41ea-b48c-58a92f61995e.jpg?auto=format",
      "productId": "313f6ded73199c8d7ba1aa8dfd0d6086b615fed8",
      "productName": "Greenlam",
      "productType": "room",
      "qty": 98,
      "price": {
        "currencyCode": "PHP",
        "value": 952
      }
    }
  ]